README.rst
setup.py
shortfuse/__init__.py
shortfuse/attributes.py
shortfuse/node.py
shortfuse/operations.py
shortfuse.egg-info/PKG-INFO
shortfuse.egg-info/SOURCES.txt
shortfuse.egg-info/dependency_links.txt
shortfuse.egg-info/requires.txt
shortfuse.egg-info/top_level.txt
shortfuse/extra/__init__.py
shortfuse/extra/local.py
shortfuse/extra/memory.py
shortfuse_test/__init__.py
shortfuse_test/concurrency.py
shortfuse_test/fixtures.py
shortfuse_test/integration.py
shortfuse_test/mount.py