Metadata-Version: 1.0
Name: shortfuse
Version: 0.0.30
Summary: shortfuse is a lightweight wrapper around fusepy
Home-page: UNKNOWN
Author: Red Balloon Security
Author-email: quack-tech@redballoonsecurity.com
License: UNKNOWN
Platform: UNKNOWN
